pyrando
