Metadata-Version: 1.2
Name: pyrando
Version: 0.3.0
Summary: Python module for Random.org JSON API
Home-page: https://github.com/dfundingsland/pyrando
Author: David Fundingsland
Author-email: david@fundings.land
License: MIT
Download-URL: https://github.com/dfundingsland/pyrando/master.zip
Platform: UNKNOWN
Classifier: Development Status :: 3 - Alpha
Classifier: Intended Audience :: Developers
Classifier: Natural Language :: English
Classifier: License :: OSI Approved :: MIT License
Classifier: Programming Language :: Python
Classifier: Programming Language :: Python :: 3.6
Requires-Python: >=3.6
